selas/__init__.py
selas/cli.py
selas/database.py
selas-0.0.2.dist-info/LICENSE
selas-0.0.2.dist-info/METADATA
selas-0.0.2.dist-info/WHEEL
selas-0.0.2.dist-info/entry_points.txt
selas-0.0.2.dist-info/top_level.txt
selas-0.0.2.dist-info/RECORD
