Metadata-Version: 2.1
Name: selas
Version: 0.0.2
Summary: Client in python to interact with selas API
Author-email: Benjamin Trom <benjamin@selas.studio>, Romeo Incardona <romeo@selas.studio>
License: MIT License        
Classifier: Programming Language :: Python :: 3
Classifier: License :: OSI Approved :: MIT License
Classifier: Operating System :: OS Independent
Requires-Python: >=3.8
License-File: LICENSE
Requires-Dist: pydantic (>=1.9.1)
Requires-Dist: loguru (>=0.6.0)
Requires-Dist: tomli (>=2.0.1)
Requires-Dist: typer (>=0.6.1)
Requires-Dist: python-dotenv (>=0.21.0)
Requires-Dist: GitPython (>=3.1.0)
Requires-Dist: supabase (>=0.5.8)
Requires-Dist: blurhash-python (>=1.1.3)
Provides-Extra: dev
Requires-Dist: isort (>=5.10.1) ; extra == 'dev'
Requires-Dist: black (>=22.1.0) ; extra == 'dev'
Requires-Dist: flake8 (>=5.0.4) ; extra == 'dev'
Requires-Dist: mypy (>=0.971) ; extra == 'dev'
Provides-Extra: notebook
Requires-Dist: jupyter (>=1.0.0) ; extra == 'notebook'
